[{"text":"😂 heerlijk dit! https://t.co/7F91xVlZ6c","url":"https://twitter.com/dydric/status/1133101316094484488","created":"Mon May 27 20:03:00"},{"text":"Zonde! Hoog Sammy, Kijk omhoog Sammy!!! https://t.co/DcuOj37KDK","url":"https://twitter.com/dydric/status/1132592079484403712","created":"Sun May 26 10:19:28"},{"text":"RT @CafeRoubaix: 25 May '79: Saronni gets his first maglia rosa, wins Giro\n25 May '94: Berzin gets his first maglia rosa, wins Giro\n25 May…","url":"https://twitter.com/dydric/status/1132544059690631174","created":"Sun May 26 07:08:40"},{"text":"RT @ADSportwereld: Organisatie Giro haalt Gavia uit het parcours wegens lawinegevaar https://t.co/05MVL3OlMI","url":"https://twitter.com/dydric/status/1132396880640532482","created":"Sat May 25 21:23:49"},{"text":"RT @JamesMelville: Dear Britain,\nIn two months time, this man is likely to be your next Prime Minister.\nGood luck with that.\n\nhttps://t.co/…","url":"https://twitter.com/dydric/status/1132239233886904320","created":"Sat May 25 10:57:24"},{"text":"Lekker aan het stappen geweest gisteren 😆 https://t.co/1FXMY6mI98","url":"https://twitter.com/dydric/status/1132214669517774848","created":"Sat May 25 09:19:47"}]